stored_context_protocol/__init__.py
stored_context_protocol/exceptions.py
stored_context_protocol/core/__init__.py
stored_context_protocol/core/context_manager.py
stored_context_protocol/core/context_selector.py
stored_context_protocol/core/models.py
stored_context_protocol/utils/__init__.py
stored_context_protocol/utils/file_loader.py
stored_context_protocol/utils/openai_helper.py
stored_context_protocol-0.2.0.dist-info/METADATA
stored_context_protocol-0.2.0.dist-info/WHEEL
stored_context_protocol-0.2.0.dist-info/top_level.txt
stored_context_protocol-0.2.0.dist-info/RECORD
