Metadata-Version: 2.4
Name: stored-context-protocol
Version: 0.2.0
Summary: A Python library for managing and retrieving contextual information using OpenAI's function calling
Home-page: https://github.com/QuitCool/stored-context-protocol
Author: SCP Team
Author-email: SCP Team <scp@olives.chat>
License: MIT
Project-URL: Homepage, https://github.com/QuitCool/stored-context-protocol
Project-URL: Bug Reports, https://github.com/QuitCool/stored-context-protocol/issues
Project-URL: Source, https://github.com/QuitCool/stored-context-protocol
Classifier: Development Status :: 3 - Alpha
Classifier: Intended Audience :: Developers
Classifier: Topic :: Software Development :: Libraries :: Python Modules
Classifier: Programming Language :: Python :: 3
Classifier: Programming Language :: Python :: 3.8
Classifier: Programming Language :: Python :: 3.9
Classifier: Programming Language :: Python :: 3.10
Classifier: Programming Language :: Python :: 3.11
Classifier: Programming Language :: Python :: 3.12
Requires-Python: >=3.8
Requires-Dist: openai>=1.0.0
Requires-Dist: python-dotenv>=0.19.0
Provides-Extra: dev
Requires-Dist: pytest>=7.0.0; extra == "dev"
Requires-Dist: pytest-cov>=4.0.0; extra == "dev"
Requires-Dist: black>=22.0.0; extra == "dev"
Requires-Dist: flake8>=4.0.0; extra == "dev"
Requires-Dist: mypy>=0.900; extra == "dev"
Dynamic: author
Dynamic: home-page
Dynamic: requires-python
